LICENSE
MANIFEST.in
README.md
requirements.txt
setup.py
bin/marathoner
bin/marathoner.bat
marathoner/__init__.py
marathoner/cmdline.py
marathoner/executor.py
marathoner/mediator.py
marathoner/project.py
marathoner/scores.py
marathoner/tag.py
marathoner.egg-info/PKG-INFO
marathoner.egg-info/SOURCES.txt
marathoner.egg-info/dependency_links.txt
marathoner.egg-info/requires.txt
marathoner.egg-info/top_level.txt
marathoner/commands/__init__.py
marathoner/commands/base.py
marathoner/commands/best.py
marathoner/commands/cached.py
marathoner/commands/clear.py
marathoner/commands/hash.py
marathoner/commands/help.py
marathoner/commands/multi_test.py
marathoner/commands/quit.py
marathoner/commands/single_test.py
marathoner/commands/tag.py
marathoner/commands/tag_create.py
marathoner/commands/tag_delete.py
marathoner/commands/tag_many.py
marathoner/commands/tag_one.py
marathoner/communicators/__init__.py
marathoner/communicators/general_communicator.py
marathoner/communicators/path_defense.py
marathoner/communicators/peg_jumping.py
marathoner/communicators/population_mapping.py
marathoner/communicators/viral_infection.py
marathoner/contest/__init__.py
marathoner/contest/base.py
marathoner/contest/simple.py
marathoner/templates/project/marathoner.cfg
marathoner/utils/__init__.py
marathoner/utils/async_reader.py
marathoner/utils/key_press.py
marathoner/utils/ossignal.py
marathoner/utils/print_table.py
marathoner/utils/proc.py
marathoner/utils/user_input.py