Metadata-Version: 1.1
Name: marathoner
Version: 1.2.18
Summary: Testing tool for TopCoder marathon matches.
Home-page: https://github.com/Mimino666/tc-marathoner
Author: Michal Mimino Danilak
Author-email: michal.danilak@gmail.com
License: The MIT License (MIT)
